{
  "routine": [
    {
      "exercise": "Wall Extensions",
      "programming": "5 - 10 reps",
      "category": "Warmup",
      "url": null,
      "image": "https://images-na.ssl-images-amazon.com/images/I/61McsadO1OL.jpg"
    },
    {
      "exercise": "Band Dislocates",
      "programming": "5 - 10 reps",
      "category": "Warmup",
      "url": null,
      "image": "https://images-na.ssl-images-amazon.com/images/I/61McsadO1OL.jpg"
    },
    {
      "exercise": "Cat-Camels",
      "programming": "5 - 10 reps",
      "category": "Warmup",
      "url": null,
      "image": "https://images-na.ssl-images-amazon.com/images/I/61McsadO1OL.jpg"
    },
    {
      "exercise": "Scapular Shrugs",
      "programming": "5 - 10 reps",
      "category": "Warmup",
      "url": null,
      "image": "https://images-na.ssl-images-amazon.com/images/I/61McsadO1OL.jpg"
    },
    {
      "exercise": "Full Body Circles",
      "programming": "5 - 10 reps",
      "category": "Warmup",
      "url": null,
      "image": "https://images-na.ssl-images-amazon.com/images/I/61McsadO1OL.jpg"
    },
    {
      "exercise": "Front Leg Swings",
      "programming": "5 - 10 reps",
      "category": "Warmup",
      "url": null,
      "image": "https://images-na.ssl-images-amazon.com/images/I/61McsadO1OL.jpg"
    },
    {
      "exercise": "Side Leg Swings",
      "programming": "5 - 10 reps",
      "category": "Warmup",
      "url": null,
      "image": "https://images-na.ssl-images-amazon.com/images/I/61McsadO1OL.jpg"
    },
    {
      "exercise": "Wrist Mobility",
      "programming": "5 - 10 reps",
      "category": "Warmup",
      "url": null,
      "image": "https://images-na.ssl-images-amazon.com/images/I/61McsadO1OL.jpg"
    },
    {
      "exercise": "Handstands",
      "programming": "5 - 10 minutes",
      "category": "Skill",
      "url": null,
      "image": "https://images-na.ssl-images-amazon.com/images/I/61McsadO1OL.jpg"
    },
    {
      "exercise": "Support",
      "programming": "2 - 3 minutes",
      "category": "Skill",
      "url": null,
      "image": "https://images-na.ssl-images-amazon.com/images/I/61McsadO1OL.jpg"
    },
    {
      "exercise": "Pullups",
      "programming": "3x 5 - 8 reps",
      "category": "Strength",
      "url": null,
      "image": "https://images-na.ssl-images-amazon.com/images/I/61McsadO1OL.jpg"
    },
    {
      "exercise": "Dips",
      "programming": "3x 5 - 8 reps",
      "category": "Strength",
      "url": null,
      "image": "https://images-na.ssl-images-amazon.com/images/I/61McsadO1OL.jpg"
    },
    {
      "exercise": "Squats",
      "programming": "Squats: 3x 5 - 8 reps",
      "category": "Strength",
      "url": null,
      "image": "https://images-na.ssl-images-amazon.com/images/I/61McsadO1OL.jpg"
    },
    {
      "exercise": "L-Sits",
      "programming": "3x 5 - 8 reps",
      "category": "Strength",
      "url": null,
      "image": "https://images-na.ssl-images-amazon.com/images/I/61McsadO1OL.jpg"
    },
    {
      "exercise": "Pushups",
      "programming": "3x 5 - 8 reps",
      "category": "Strength",
      "url": null,
      "image": "https://images-na.ssl-images-amazon.com/images/I/61McsadO1OL.jpg"
    },
    {
      "exercise": "Rows",
      "programming": "3x 5 - 8 reps",
      "category": "Strength",
      "url": null,
      "image": "https://images-na.ssl-images-amazon.com/images/I/61McsadO1OL.jpg"
    }
  ]
}